{
  "minecraft:recipes/decorations/stone_brick_walls_from_stone_stonecutting": {
    "criteria": {
      "has_stone": "2022-04-02 00:29:45 +0200"
    },
    "done": true
  },
  "minecraft:recipes/building_blocks/stone_brick_stairs_from_stone_stonecutting": {
    "criteria": {
      "has_stone": "2022-04-02 00:29:45 +0200"
    },
    "done": true
  },
  "minecraft:recipes/transportation/dark_oak_boat": {
    "criteria": {
      "in_water": "2022-04-02 01:30:33 +0200"
    },
    "done": true
  },
  "minecraft:recipes/building_blocks/stone_stairs_from_stone_stonecutting": {
    "criteria": {
      "has_stone": "2022-04-02 00:29:45 +0200"
    },
    "done": true
  },
  "minecraft:nether/obtain_crying_obsidian": {
    "criteria": {
      "crying_obsidian": "2022-04-02 01:04:58 +0200"
    },
    "done": true
  },
  "minecraft:recipes/building_blocks/stone_bricks": {
    "criteria": {
      "has_stone": "2022-04-02 00:29:45 +0200"
    },
    "done": true
  },
  "minecraft:recipes/building_blocks/stone_bricks_from_stone_stonecutting": {
    "criteria": {
      "has_stone": "2022-04-02 00:29:45 +0200"
    },
    "done": true
  },
  "minecraft:recipes/decorations/respawn_anchor": {
    "criteria": {
      "has_obsidian": "2022-04-02 01:04:58 +0200"
    },
    "done": true
  },
  "minecraft:recipes/decorations/stonecutter": {
    "criteria": {
      "has_stone": "2022-04-02 00:29:45 +0200"
    },
    "done": true
  },
  "minecraft:recipes/building_blocks/stone_stairs": {
    "criteria": {
      "has_stone": "2022-04-02 00:29:45 +0200"
    },
    "done": true
  },
  "minecraft:adventure/adventuring_time": {
    "criteria": {
      "minecraft:taiga": "2022-04-02 00:27:16 +0200",
      "minecraft:taiga_hills": "2022-04-02 00:26:14 +0200",
      "minecraft:river": "2022-04-02 09:18:21 +0200",
      "minecraft:plains": "2022-04-02 09:18:18 +0200"
    },
    "done": false
  },
  "minecraft:recipes/building_blocks/smooth_stone": {
    "criteria": {
      "has_stone": "2022-04-02 00:29:45 +0200"
    },
    "done": true
  },
  "minecraft:recipes/transportation/birch_boat": {
    "criteria": {
      "in_water": "2022-04-02 01:30:33 +0200"
    },
    "done": true
  },
  "minecraft:recipes/decorations/chest": {
    "criteria": {
      "has_lots_of_items": "2022-04-02 08:52:44 +0200"
    },
    "done": true
  },
  "minecraft:recipes/building_blocks/stone_slab_from_stone_stonecutting": {
    "criteria": {
      "has_stone": "2022-04-02 00:29:45 +0200"
    },
    "done": true
  },
  "minecraft:recipes/building_blocks/chiseled_stone_bricks_stone_from_stonecutting": {
    "criteria": {
      "has_stone": "2022-04-02 00:29:45 +0200"
    },
    "done": true
  },
  "minecraft:recipes/redstone/stone_button": {
    "criteria": {
      "has_stone": "2022-04-02 00:29:45 +0200"
    },
    "done": true
  },
  "minecraft:recipes/transportation/acacia_boat": {
    "criteria": {
      "in_water": "2022-04-02 01:30:33 +0200"
    },
    "done": true
  },
  "minecraft:recipes/transportation/oak_boat": {
    "criteria": {
      "in_water": "2022-04-02 01:30:33 +0200"
    },
    "done": true
  },
  "minecraft:recipes/building_blocks/stone_slab": {
    "criteria": {
      "has_stone": "2022-04-02 00:29:45 +0200"
    },
    "done": true
  },
  "minecraft:recipes/redstone/stone_pressure_plate": {
    "criteria": {
      "has_stone": "2022-04-02 00:29:45 +0200"
    },
    "done": true
  },
  "minecraft:adventure/root": {
    "criteria": {
      "killed_something": "2022-04-02 09:19:54 +0200"
    },
    "done": true
  },
  "minecraft:recipes/building_blocks/stone_brick_slab_from_stone_stonecutting": {
    "criteria": {
      "has_stone": "2022-04-02 00:29:45 +0200"
    },
    "done": true
  },
  "minecraft:recipes/transportation/jungle_boat": {
    "criteria": {
      "in_water": "2022-04-02 01:30:33 +0200"
    },
    "done": true
  },
  "minecraft:recipes/transportation/spruce_boat": {
    "criteria": {
      "in_water": "2022-04-02 01:30:33 +0200"
    },
    "done": true
  },
  "DataVersion": 2730
}